{
    "fluentMethods": true,
    "relationships": [],
    "fields": [
        {
            "fieldName": "caption",
            "fieldType": "String"
        },
        {
            "fieldName": "image",
            "fieldType": "byte[]",
            "fieldTypeBlobContent": "image"
        },
        {
            "fieldName": "imageContentType",
            "fieldType": "String"
        },
        {
            "fieldName": "createdDate",
            "fieldType": "ZonedDateTime"
        },
        {
            "fieldName": "modifiedDate",
            "fieldType": "ZonedDateTime"
        }
    ],
    "dto": "no",
    "service": "no",
    "entityTableName": "media",
    "pagination": "infinite-scroll"
}
